msm/__init__.py
msm/__main__.py
msm/exceptions.py
msm/mycroft_skills_manager.py
msm/skill_entry.py
msm/skill_repo.py
msm/skill_state.py
msm/util.py
msm-0.9.0.dist-info/LICENSE
msm-0.9.0.dist-info/METADATA
msm-0.9.0.dist-info/WHEEL
msm-0.9.0.dist-info/entry_points.txt
msm-0.9.0.dist-info/top_level.txt
msm-0.9.0.dist-info/RECORD
