Metadata-Version: 2.1
Name: msm
Version: 0.9.0
Summary: Mycroft Skills Manager
Home-page: https://github.com/MycroftAI/mycroft-skills-manager
Author: jarbasAI, Matthew Scholefield, Mycroft AI
Author-email: jarbasai@mailfence.com, matthew331199@gmail.com, dev@mycroft.ai
License: Apache-2.0
Platform: UNKNOWN
Classifier: Development Status :: 4 - Beta
Classifier: Intended Audience :: Developers
Classifier: License :: OSI Approved :: Apache Software License
Classifier: Programming Language :: Python :: 3.6
Classifier: Programming Language :: Python :: 3.7
Classifier: Programming Language :: Python :: 3.8
Classifier: Programming Language :: Python :: 3.9
Requires-Python: >=3.6
Requires-Dist: GitPython
Requires-Dist: fasteners
Requires-Dist: lazy
Requires-Dist: pako
Requires-Dist: pyxdg
Requires-Dist: pyyaml
Requires-Dist: requests
